[
  {
    "player": "Moppi-Anub'Arak",
    "date": "1/1/30",
    "time": "19:53:46",
    "id": "1710698026-9",
    "itemID": 207167,
    "itemString": "item:207167::::::::70:70::5:5:6652:7980:9570:1504:8767",
    "response": "Gebot",
    "votes": 0,
    "class": "DEMONHUNTER",
    "instance": "Amirdrassil, the Dream's Hope-Heroic",
    "boss": "Smolderon",
    "gear1": "[Witherbark's Branch]",
    "gear2": "[Ember of Nullification]",
    "responseID": "1",
    "isAwardReason": "false",
    "rollType": "normal",
    "subType": "Miscellaneous",
    "equipLoc": "Trinket",
    "note": "30",
    "owner": "Moppi-Anub'arak",
    "itemName": "Ashes of the Embersoul"
  }
]